geoplots/__init__.py
geoplots/_const.py
geoplots/bound.py
geoplots/boxplot.py
geoplots/cartopy.py
geoplots/color.py
geoplots/heatmap.py
geoplots/legend.py
geoplots/wrapper.py
geoplots/icongrid/__init__.py
geoplots/icongrid/fontawesome_mapping.py
geoplots/icongrid/icongrid.py
geoplots/icongrid/icons/fa-brands-400.ttf
geoplots/icongrid/icons/fa-regular-400.ttf
geoplots/icongrid/icons/fa-solid-900.ttf
geoplots-0.1.9.dist-info/licenses/LICENSE
geoplots-0.1.9.dist-info/METADATA
geoplots-0.1.9.dist-info/WHEEL
geoplots-0.1.9.dist-info/top_level.txt
geoplots-0.1.9.dist-info/RECORD
